schedule_kspc/__init__.py
schedule_kspc/DirManager.py
schedule_kspc/ExcelParser.py
schedule_kspc/JsonAdapter.py
schedule_kspc/Store.py
schedule_kspc/WebRequests.py
schedule_kspc-1.0.6.dist-info/METADATA
schedule_kspc-1.0.6.dist-info/WHEEL
schedule_kspc-1.0.6.dist-info/RECORD
