Metadata-Version: 2.1
Name: schedule-kspc
Version: 1.0.6
Summary: Automatic schedule for Kursk State Polytechnic College (KSPC)
Home-page: https://github.com/bonkibon-education/schedule-kspc
License: License :: OSI Approved :: GNU Affero General Public License v3
Author: LeoBonki
Author-email: bonkibon75@gmail.com
Requires-Python: >=3.10,<4.0
Classifier: License :: Other/Proprietary License
Classifier: Programming Language :: Python :: 3
Classifier: Programming Language :: Python :: 3.10
Classifier: Programming Language :: Python :: 3.11
Classifier: Programming Language :: Python :: 3.12
Requires-Dist: aiofiles
Requires-Dist: aiohttp
Requires-Dist: numpy
Requires-Dist: openpyxl
Requires-Dist: requests
Project-URL: Repository, https://codeload.github.com/bonkibon-education/schedule-kspc/zip/refs/tags/v1.0-beta
